{
  "id": "if-i-were-free",
  "title": "If I Were Free",
  "key": "D",
  "reviewed": true,
  "sections": [
    {
      "name": "Verse 1",
      "lines": [
        {
          "tokens": [
            {
              "chord": "D",
              "lyric": "If I were fr"
            },
            {
              "chord": "A7",
              "lyric": "ee to speak my min"
            },
            {
              "chord": "D",
              "lyric": "d,"
            }
          ],
          "raw": "[D]If I were fr[A7]ee to speak my min[D]d,"
        },
        {
          "tokens": [
            {
              "chord": "A7",
              "lyric": "I'd tell a t"
            },
            {
              "chord": "G",
              "lyric": "ale to all manki"
            },
            {
              "chord": "A7",
              "lyric": "nd."
            }
          ],
          "raw": "[A7]I'd tell a t[G]ale to all manki[A7]nd."
        },
        {
          "tokens": [
            {
              "chord": null,
              "lyric": "Of how the flow"
            },
            {
              "chord": "D",
              "lyric": "ers do "
            },
            {
              "chord": "D7",
              "lyric": "bloom and f"
            },
            {
              "chord": "G",
              "lyric": "ade,"
            }
          ],
          "raw": "Of how the flow[D]ers do [D7]bloom and f[G]ade,"
        },
        {
          "tokens": [
            {
              "chord": null,
              "lyric": "Of how we f"
            },
            {
              "chord": "D",
              "lyric": "ought and ho"
            },
            {
              "chord": "A7",
              "lyric": "w we gain"
            },
            {
              "chord": "D",
              "lyric": "ed."
            }
          ],
          "raw": "Of how we f[D]ought and ho[A7]w we gain[D]ed."
        },
        {
          "tokens": [
            {
              "chord": null,
              "lyric": ""
            }
          ],
          "raw": ""
        }
      ]
    },
    {
      "name": "Verse 2",
      "lines": [
        {
          "tokens": [
            {
              "chord": null,
              "lyric": "This weary world has had its fill"
            }
          ],
          "raw": "This weary world has had its fill"
        },
        {
          "tokens": [
            {
              "chord": null,
              "lyric": "Of words of war on ev'ry hill."
            }
          ],
          "raw": "Of words of war on ev'ry hill."
        },
        {
          "tokens": [
            {
              "chord": null,
              "lyric": "The time has come for peaceful days"
            }
          ],
          "raw": "The time has come for peaceful days"
        },
        {
          "tokens": [
            {
              "chord": null,
              "lyric": "For peaceful men and peaceful ways."
            }
          ],
          "raw": "For peaceful men and peaceful ways."
        },
        {
          "tokens": [
            {
              "chord": null,
              "lyric": ""
            }
          ],
          "raw": ""
        }
      ]
    },
    {
      "name": "Verse 3",
      "lines": [
        {
          "tokens": [
            {
              "chord": null,
              "lyric": "When all mankind has ceased to fight"
            }
          ],
          "raw": "When all mankind has ceased to fight"
        },
        {
          "tokens": [
            {
              "chord": null,
              "lyric": "I'll raise my head in thanks each night."
            }
          ],
          "raw": "I'll raise my head in thanks each night."
        },
        {
          "tokens": [
            {
              "chord": null,
              "lyric": "For this great love and all it means,"
            }
          ],
          "raw": "For this great love and all it means,"
        },
        {
          "tokens": [
            {
              "chord": null,
              "lyric": "For golden days and peaceful dreams."
            }
          ],
          "raw": "For golden days and peaceful dreams."
        },
        {
          "tokens": [
            {
              "chord": null,
              "lyric": ""
            }
          ],
          "raw": ""
        }
      ]
    },
    {
      "name": "Verse 4",
      "lines": [
        {
          "tokens": [
            {
              "chord": "E",
              "lyric": "If I were fr"
            },
            {
              "chord": "B7",
              "lyric": "ee to speak my min"
            },
            {
              "chord": "E",
              "lyric": "d,"
            }
          ],
          "raw": "[E]If I were fr[B7]ee to speak my min[E]d,"
        },
        {
          "tokens": [
            {
              "chord": "E7",
              "lyric": "I'd tell a t"
            },
            {
              "chord": "A",
              "lyric": "ale to all mankin"
            },
            {
              "chord": "B7",
              "lyric": "d."
            }
          ],
          "raw": "[E7]I'd tell a t[A]ale to all mankin[B7]d."
        },
        {
          "tokens": [
            {
              "chord": null,
              "lyric": "Of how the flow"
            },
            {
              "chord": "E",
              "lyric": "ers do b"
            },
            {
              "chord": "E7",
              "lyric": "loom and f"
            },
            {
              "chord": "A",
              "lyric": "ade,"
            }
          ],
          "raw": "Of how the flow[E]ers do b[E7]loom and f[A]ade,"
        },
        {
          "tokens": [
            {
              "chord": null,
              "lyric": "Of how we f"
            },
            {
              "chord": "E",
              "lyric": "ought and how"
            },
            {
              "chord": "B7",
              "lyric": " we gaine"
            },
            {
              "chord": "E",
              "lyric": "d."
            }
          ],
          "raw": "Of how we f[E]ought and how[B7] we gaine[E]d."
        },
        {
          "tokens": [
            {
              "chord": null,
              "lyric": ""
            }
          ],
          "raw": ""
        }
      ]
    }
  ],
  "sourcePath": "songs/if-i-were-free.pro",
  "source": "{title: If I Were Free}\n{key: D}\n{reviewed: true}\n\n{section: Verse 1}\n[D]If I were fr[A7]ee to speak my min[D]d,\n[A7]I'd tell a t[G]ale to all manki[A7]nd.\nOf how the flow[D]ers do [D7]bloom and f[G]ade,\nOf how we f[D]ought and ho[A7]w we gain[D]ed.\n\n{section: Verse 2}\nThis weary world has had its fill\nOf words of war on ev'ry hill.\nThe time has come for peaceful days\nFor peaceful men and peaceful ways.\n\n{section: Verse 3}\nWhen all mankind has ceased to fight\nI'll raise my head in thanks each night.\nFor this great love and all it means,\nFor golden days and peaceful dreams.\n\n{section: Verse 4}\n[E]If I were fr[B7]ee to speak my min[E]d,\n[E7]I'd tell a t[A]ale to all mankin[B7]d.\nOf how the flow[E]ers do b[E7]loom and f[A]ade,\nOf how we f[E]ought and how[B7] we gaine[E]d.\n"
}