{
  "id": "my-cross",
  "title": "My Cross",
  "key": "G",
  "sections": [
    {
      "name": "Verse",
      "lines": [
        {
          "tokens": [
            {
              "chord": null,
              "lyric": ""
            }
          ],
          "raw": ""
        }
      ]
    },
    {
      "name": "Verse 1",
      "lines": [
        {
          "tokens": [
            {
              "chord": "G",
              "lyric": "Who can I go to for my help to bear my heavy cross?"
            }
          ],
          "raw": "[G]Who can I go to for my help to bear my heavy cross?"
        },
        {
          "tokens": [
            {
              "chord": "C",
              "lyric": "Has not the Lord been helping me before I ever knew?"
            }
          ],
          "raw": "[C]Has not the Lord been helping me before I ever knew?"
        },
        {
          "tokens": [
            {
              "chord": "G",
              "lyric": "Because I had no strength to bear the load He gave to me,"
            }
          ],
          "raw": "[G]Because I had no strength to bear the load He gave to me,"
        },
        {
          "tokens": [
            {
              "chord": "Em",
              "lyric": "Six thousand yeas of blood was shed, the thorny path prolonged."
            }
          ],
          "raw": "[Em]Six thousand yeas of blood was shed, the thorny path prolonged."
        },
        {
          "tokens": [
            {
              "chord": null,
              "lyric": ""
            }
          ],
          "raw": ""
        }
      ]
    },
    {
      "name": "Chorus",
      "lines": [
        {
          "tokens": [
            {
              "chord": "Am7",
              "lyric": "I will shoulder now the cross, and pledge I shall endure;"
            }
          ],
          "raw": "[Am7]I will shoulder now the cross, and pledge I shall endure;"
        },
        {
          "tokens": [
            {
              "chord": "D",
              "lyric": "Far beyond Golgotha's pain, now hear the victory."
            }
          ],
          "raw": "[D]Far beyond Golgotha's pain, now hear the victory."
        },
        {
          "tokens": [
            {
              "chord": null,
              "lyric": ""
            }
          ],
          "raw": ""
        }
      ]
    },
    {
      "name": "Verse 2",
      "lines": [
        {
          "tokens": [
            {
              "chord": "G",
              "lyric": "The Lord would never give to me a cross I could not bear."
            }
          ],
          "raw": "[G]The Lord would never give to me a cross I could not bear."
        },
        {
          "tokens": [
            {
              "chord": "C",
              "lyric": "If I give all the strength I have I shall achieve the goal."
            }
          ],
          "raw": "[C]If I give all the strength I have I shall achieve the goal."
        },
        {
          "tokens": [
            {
              "chord": "G",
              "lyric": "I sacrifice to do His will, no trial I cannot bear."
            }
          ],
          "raw": "[G]I sacrifice to do His will, no trial I cannot bear."
        },
        {
          "tokens": [
            {
              "chord": "Am7",
              "lyric": "I give my life to go this way, no one can turn me back."
            }
          ],
          "raw": "[Am7]I give my life to go this way, no one can turn me back."
        },
        {
          "tokens": [
            {
              "chord": null,
              "lyric": ""
            }
          ],
          "raw": ""
        }
      ]
    },
    {
      "name": "Verse 3",
      "lines": [
        {
          "tokens": [
            {
              "chord": "D7",
              "lyric": "Our Father always persevered to see His will be done,"
            }
          ],
          "raw": "[D7]Our Father always persevered to see His will be done,"
        },
        {
          "tokens": [
            {
              "chord": "G",
              "lyric": "If all His children join the task it soon will be achieved."
            }
          ],
          "raw": "[G]If all His children join the task it soon will be achieved."
        },
        {
          "tokens": [
            {
              "chord": "C",
              "lyric": "If not, the lonely years of strife will all have been in vain."
            }
          ],
          "raw": "[C]If not, the lonely years of strife will all have been in vain."
        },
        {
          "tokens": [
            {
              "chord": "G",
              "lyric": "No matter what, in fighting on, we'll win eternal joy."
            }
          ],
          "raw": "[G]No matter what, in fighting on, we'll win eternal joy."
        },
        {
          "tokens": [
            {
              "chord": null,
              "lyric": ""
            }
          ],
          "raw": ""
        }
      ]
    }
  ],
  "sourcePath": "songs/my-cross.pro",
  "source": "{title: My Cross}\n{key: G}\n\n{section: Verse 1}\n[G]Who can I go to for my help to bear my heavy cross?\n[C]Has not the Lord been helping me before I ever knew?\n[G]Because I had no strength to bear the load He gave to me,\n[Em]Six thousand yeas of blood was shed, the thorny path prolonged.\n\n{section: Chorus}\n[Am7]I will shoulder now the cross, and pledge I shall endure;\n[D]Far beyond Golgotha's pain, now hear the victory.\n\n{section: Verse 2}\n[G]The Lord would never give to me a cross I could not bear.\n[C]If I give all the strength I have I shall achieve the goal.\n[G]I sacrifice to do His will, no trial I cannot bear.\n[Am7]I give my life to go this way, no one can turn me back.\n\n{section: Verse 3}\n[D7]Our Father always persevered to see His will be done,\n[G]If all His children join the task it soon will be achieved.\n[C]If not, the lonely years of strife will all have been in vain.\n[G]No matter what, in fighting on, we'll win eternal joy.\n"
}